humanizer_portugues/__init__.py
humanizer_portugues/filesize.py
humanizer_portugues/list.py
humanizer_portugues/number.py
humanizer_portugues/py.typed
humanizer_portugues/time.py
humanizer_portugues-2.4.1.dist-info/LICENSE.rst
humanizer_portugues-2.4.1.dist-info/WHEEL
humanizer_portugues-2.4.1.dist-info/METADATA
humanizer_portugues-2.4.1.dist-info/RECORD
