Metadata-Version: 2.1
Name: humanizer-portugues
Version: 2.4.1
Summary: Humanize functions for Portuguese.
Home-page: https://github.com/staticdev/humanizer-portugues
License: MIT
Author: Thiago Carvalho D'Ávila
Author-email: thiagocavila@gmail.com
Requires-Python: >=3.7,<4.0
Classifier: Development Status :: 7 - Inactive
Classifier: Intended Audience :: Developers
Classifier: License :: OSI Approved :: MIT License
Classifier: Programming Language :: Python
Classifier: Programming Language :: Python :: 3
Classifier: Programming Language :: Python :: 3.7
Classifier: Programming Language :: Python :: 3.8
Classifier: Programming Language :: Python :: 3.9
Project-URL: Changelog, https://github.com/staticdev/humanizer-portugues/releases
Project-URL: Documentation, https://humanizer-portugues.readthedocs.io
Project-URL: Repository, https://github.com/staticdev/humanizer-portugues
